acdh_geonames_utils/__init__.py
acdh_geonames_utils/acdh_geonames_utils.py
acdh_geonames_utils/cli.py
acdh_geonames_utils/config.py
acdh_geonames_utils/gn_client.py
acdh_geonames_utils/utils.py
acdh_geonames_utils-0.5.0.dist-info/AUTHORS.rst
acdh_geonames_utils-0.5.0.dist-info/LICENSE
acdh_geonames_utils-0.5.0.dist-info/METADATA
acdh_geonames_utils-0.5.0.dist-info/WHEEL
acdh_geonames_utils-0.5.0.dist-info/entry_points.txt
acdh_geonames_utils-0.5.0.dist-info/top_level.txt
acdh_geonames_utils-0.5.0.dist-info/RECORD
