Metadata-Version: 2.1
Name: acdh-geonames-utils
Version: 0.5.0
Summary: Utility functions to interact with geonames.org
Home-page: https://github.com/acdh-oeaw/acdh_geonames_utils
Author: Peter Andorfer
Author-email: peter.andorfer@oeaw.ac.at
License: MIT license
Keywords: acdh_geonames_utils
Platform: UNKNOWN
Classifier: Development Status :: 2 - Pre-Alpha
Classifier: Intended Audience :: Developers
Classifier: License :: OSI Approved :: MIT License
Classifier: Natural Language :: English
Classifier: Programming Language :: Python :: 3
Classifier: Programming Language :: Python :: 3.8
Requires-Python: >=3.8
Requires-Dist: Click (>=7.0)
Requires-Dist: requests
Requires-Dist: pandas (>=1.1)
Requires-Dist: lxml (>4.6)
